powerpoint_templates/__init__.py
powerpoint_templates/business_template_examples.py
powerpoint_templates/cli.py
powerpoint_templates/enhanced_business_dsl.py
powerpoint_templates/enhanced_visual_generator.py
powerpoint_templates/integration_examples.py
powerpoint_templates/modular_components.py
powerpoint_templates/template_system_design.py
powerpoint_template_system-1.0.6.dist-info/LICENSE
powerpoint_template_system-1.0.6.dist-info/METADATA
powerpoint_template_system-1.0.6.dist-info/WHEEL
powerpoint_template_system-1.0.6.dist-info/entry_points.txt
powerpoint_template_system-1.0.6.dist-info/top_level.txt
powerpoint_template_system-1.0.6.dist-info/RECORD
