Metadata-Version: 2.1
Name: powerpoint-template-system
Version: 1.0.6
Summary: A comprehensive template system for creating professional business presentations with modern styling, cards, and badges
Home-page: https://github.com/cpro/powerpoint-template-system
Author: PowerPoint Template System Team
Author-email: templates@cpro.com
Keywords: powerpoint,presentation,template,business,slides,pptx,cards,badges,modern-styling,gradients,shadows,typography,dsl,domain-specific-language,visual-generator,professional
Platform: any
Classifier: Development Status :: 4 - Beta
Classifier: Intended Audience :: Developers
Classifier: Intended Audience :: End Users/Desktop
Classifier: Intended Audience :: Financial and Insurance Industry
Classifier: Intended Audience :: Science/Research
Classifier: Topic :: Office/Business :: Office Suites
Classifier: Topic :: Software Development :: Libraries :: Python Modules
Classifier: Topic :: Multimedia :: Graphics :: Presentation
Classifier: Programming Language :: Python :: 3
Classifier: Programming Language :: Python :: 3.7
Classifier: Programming Language :: Python :: 3.8
Classifier: Programming Language :: Python :: 3.9
Classifier: Programming Language :: Python :: 3.10
Classifier: Programming Language :: Python :: 3.11
Classifier: Programming Language :: Python :: 3.12
Classifier: Operating System :: OS Independent
Classifier: Operating System :: Microsoft :: Windows
Classifier: Operating System :: POSIX :: Linux
Classifier: Operating System :: MacOS
Requires-Python: >=3.7
License-File: LICENSE
Requires-Dist: python-pptx >=1.0.0
Requires-Dist: lxml >=4.6.0
Requires-Dist: Pillow >=8.0.0
Requires-Dist: XlsxWriter >=3.0.0
Requires-Dist: pytest >=6.0.0
Requires-Dist: pytest-cov >=2.10.0
Requires-Dist: black >=21.0.0
Requires-Dist: flake8 >=3.8.0
Requires-Dist: sphinx >=4.0.0
Requires-Dist: sphinx-rtd-theme >=1.0.0
Provides-Extra: dev
Requires-Dist: pytest >=6.0.0 ; extra == 'dev'
Requires-Dist: pytest-cov >=2.10.0 ; extra == 'dev'
Requires-Dist: black >=21.0.0 ; extra == 'dev'
Requires-Dist: flake8 >=3.8.0 ; extra == 'dev'
Requires-Dist: mypy >=0.910 ; extra == 'dev'
Requires-Dist: pre-commit >=2.15.0 ; extra == 'dev'
Provides-Extra: docs
Requires-Dist: sphinx >=4.0.0 ; extra == 'docs'
Requires-Dist: sphinx-rtd-theme >=1.0.0 ; extra == 'docs'
Requires-Dist: sphinx-autodoc-typehints >=1.12.0 ; extra == 'docs'
Provides-Extra: examples
Requires-Dist: matplotlib >=3.3.0 ; extra == 'examples'
Requires-Dist: pandas >=1.3.0 ; extra == 'examples'
